j_realty_api/__init__.py
j_realty_api/j_realty_en.py
j_realty_api/j_realty_jp.py
j_realty_api/data/jp_prop_transaction_col_names.json
j_realty_api/data/pref-code-en.json
j_realty_api/data/pref-code-jp.json
j_realty_api-0.2.dist-info/LICENSE
j_realty_api-0.2.dist-info/METADATA
j_realty_api-0.2.dist-info/WHEEL
j_realty_api-0.2.dist-info/top_level.txt
j_realty_api-0.2.dist-info/RECORD
