Metadata-Version: 2.1
Name: j-realty-api
Version: 0.2
Summary: j_realty_api: Knowing the real estate transaction prices in Japan.
Author-email: HideyukiO <hogawa098@gmail.com>
License: MIT License
Project-URL: Repository, https://github.com/mazarimono/j_realty_api
Keywords: japan,real estate transaction price
Classifier: Programming Language :: Python :: 3
Classifier: Programming Language :: Python :: 3.10
Classifier: Programming Language :: Python :: 3.11
Requires-Python: >=3.10
License-File: LICENSE
Requires-Dist: requests
Requires-Dist: pandas
Requires-Dist: jpyforex
Provides-Extra: dev
Requires-Dist: black ; extra == 'dev'
Requires-Dist: isort ; extra == 'dev'
Requires-Dist: flake8 ; extra == 'dev'
Requires-Dist: mypy ; extra == 'dev'
Requires-Dist: pytest ; extra == 'dev'
